setup.py
daveluo_utils.egg-info/PKG-INFO
daveluo_utils.egg-info/SOURCES.txt
daveluo_utils.egg-info/dependency_links.txt
daveluo_utils.egg-info/top_level.txt
utils/Assets.py
utils/__init__.py