Metadata-Version: 1.0
Name: daveluo-utils
Version: 0.1
Summary: 一些开发常用的工具
Home-page: http://www.baidu.com
Author: Dave Luo
Author-email: kitsudo163@163.com
License: Free
Keywords: daveluo,utils
Platform: any
